movie.py
film-1.0.0.dist-info/METADATA
film-1.0.0.dist-info/WHEEL
film-1.0.0.dist-info/entry_points.txt
film-1.0.0.dist-info/top_level.txt
film-1.0.0.dist-info/RECORD
