Metadata-Version: 2.1
Name: film
Version: 1.0.0
Summary: Rename and organize movies
Home-page: https://github.com/dmkskn/m
Author: Dima Koskin
Author-email: dmksknn@gmail.com
License: MIT
Platform: UNKNOWN
Requires-Python: >=3.7
Requires-Dist: isle
